traderep/__init__.py
traderep/__main__.py
traderep/display_value.py
traderep/parse_pdfs.py
traderep/traderep.py
traderep-1.0.dist-info/LICENSE
traderep-1.0.dist-info/METADATA
traderep-1.0.dist-info/WHEEL
traderep-1.0.dist-info/entry_points.txt
traderep-1.0.dist-info/top_level.txt
traderep-1.0.dist-info/RECORD
