Metadata-Version: 2.1
Name: traderep
Version: 1.0
Summary: Application for parsing positions and         displaying their current market value
Home-page: https://github.com/Giebisch/TradeRepublic-Overview
Author: Giebisch
Author-email: rafael@giebisch-mail.de
License: UNKNOWN
Platform: UNKNOWN
Classifier: Programming Language :: Python :: 3
Classifier: License :: OSI Approved :: MIT License
Classifier: Operating System :: OS Independent
Requires-Python: >=3.6
